quickdiscord/__init__.py
quickdiscord/__main__.py
quickdiscord/generator.py
quickdiscord/templates.py
quickdiscord/utils.py
quickdiscord-1.0.2.dist-info/LICENSE
quickdiscord-1.0.2.dist-info/METADATA
quickdiscord-1.0.2.dist-info/WHEEL
quickdiscord-1.0.2.dist-info/top_level.txt
quickdiscord-1.0.2.dist-info/RECORD
