Metadata-Version: 2.2
Name: quickdiscord
Version: 1.0.2
Summary: A simple Quick discord bot generator that will make all the necessary starter files.
Home-page: https://github.com/ibrahims-main/QuickDiscord
Author: Ibrahim Mohsin
Author-email: codingstudentbruh@gmail.com
Classifier: Programming Language :: Python :: 3
Classifier: License :: OSI Approved :: MIT License
Classifier: Operating System :: OS Independent
Requires-Python: >=3.8
License-File: LICENSE
Requires-Dist: InquirerPy
Dynamic: author
Dynamic: author-email
Dynamic: classifier
Dynamic: description
Dynamic: description-content-type
Dynamic: home-page
Dynamic: requires-dist
Dynamic: requires-python
Dynamic: summary
